testcases/TestInputs/HistoryReference.json
testcases/TestInputs/TestNode100No.json
testcases/TestInputs/TestNode200_No.json
testcases/TestInputs/Test_add_coverage.json
testcases/TestInputs/Test_add_line_practitioner.json
testcases/TestInputs/Test_add_patient.json
testcases/TestInputs/Test_add_practitioner.json
testcases/TestInputs/Test_add_rel_person.json
testcases/TestInputs/Test_add_rend_prov.json
testcases/TestInputs/__init__.py
testcases/__init__.py
testcases/dsl.py
testcases/history.py
testcases/requirements.txt
testcases/serialization.py
testcases/tc1-new.json
testcases/test_claims.py
testcases/testcase.py
policy_scaffolding_python-0.2.13.dist-info/WHEEL
policy_scaffolding_python-0.2.13.dist-info/METADATA
policy_scaffolding_python-0.2.13.dist-info/RECORD
