Metadata-Version: 2.1
Name: policy-scaffolding-python
Version: 0.2.13
Summary: Scaffolding project to support Rialtic Insight Engine development in Python.
Home-page: https://rialtic.io
License: Apache-2.0
Keywords: rialtic,insight,engines,scaffolding
Author: Rialtic
Author-email: engines.data@rialtic.io
Requires-Python: >=3.7,<4.0
Classifier: Environment :: Console
Classifier: License :: OSI Approved :: Apache Software License
Classifier: Operating System :: OS Independent
Classifier: Programming Language :: Python :: 3
Classifier: Programming Language :: Python :: 3.7
Classifier: Programming Language :: Python :: 3.8
Classifier: Programming Language :: Python :: 3.9
Classifier: Topic :: Software Development :: Libraries :: Python Modules
Requires-Dist: insight-engine-schema-python (<1)
Requires-Dist: rialtic-data-dev-py (<2)
Project-URL: Repository, https://github.com/rialtic-community/policy-scaffolding-python
